{  
    "tracks":{  
       "track":[  
          {  
             "name":"isiZulu",
             "Speakers":"11587374"
          },
          {  
             "name":"isiXhosa",
             "Speakers":"8154258"
          },
          {  
             "name":"Afrikaans",
             "Speakers":"6855082"
          },
          {  
             "name":"English",
             "Speakers":"489623"
          },
          {  
             "name":"Sesotho sa Leboa",
             "Speakers":"4618576"
          },
          {  
             "name":"Setswana",
             "Speakers":"4067248"
          },
          {  
             "name":"Sesotho",
             "Speakers":"3849563"
          },
          {  
             "name":"Xitsonga",
             "Speakers":"2277148"
          },
          {  
             "name":"siSwati",
             "Speakers":"1297046"
          },
          {  
             "name":"Tshivenda",
             "Speakers":"1209388"
          },
          {  
            "name":"isiNdebele",
            "Speakers":"1090223"
         },
         {  
            "name":"Other",
            "Speakers":"828258"
         },
         {  
            "name":"Sign Language",
            "Speakers":"234655"
         }
       ]
 }
}
